gdarch/__init__.py
gdarch/cli.py
gdarch-0.1.1.dist-info/LICENSE
gdarch-0.1.1.dist-info/METADATA
gdarch-0.1.1.dist-info/WHEEL
gdarch-0.1.1.dist-info/entry_points.txt
gdarch-0.1.1.dist-info/RECORD
