Metadata-Version: 2.1
Name: gdarch
Version: 0.1.1
Summary: CLI tool to archive a Google Drive folder and replace it with the archive. Helps to free up Google Drive storage space by compressing rarely accessed folders while keeping them accessible.
Home-page: https://github.com/taross-f/gdarch
License: MIT
Keywords: google-drive,archive,compression,backup,storage-management
Author: Taro Furuya
Author-email: taro.furuya@gmail.com
Requires-Python: >=3.10,<4.0
Classifier: Development Status :: 4 - Beta
Classifier: Environment :: Console
Classifier: Intended Audience :: End Users/Desktop
Classifier: License :: OSI Approved :: MIT License
Classifier: Operating System :: OS Independent
Classifier: Programming Language :: Python :: 3
Classifier: Programming Language :: Python :: 3.10
Classifier: Programming Language :: Python :: 3.11
Classifier: Programming Language :: Python :: 3.12
Classifier: Programming Language :: Python :: 3.13
Classifier: Topic :: System :: Archiving :: Compression
Classifier: Topic :: Utilities
Requires-Dist: google-api-python-client (>=2.187.0,<3.0.0)
Requires-Dist: google-auth (>=2.15.0,<3.0.0)
Requires-Dist: google-auth-oauthlib (>=1.2.3,<2.0.0)
Requires-Dist: requests (>=2.32.5,<3.0.0)
Project-URL: Repository, https://github.com/taross-f/gdarch
